{"chunk_definitions":[{"chunk_id":"cx5mncdsy25cp","chunk_label":"unnamed-chunk-1","document_id":"43240C1D","expansion_state":0,"options":{"engine":"r","label":"unnamed-chunk-38"},"row":8,"row_count":1,"visible":true},{"chunk_id":"c8gygbgts4vde","chunk_label":"unnamed-chunk-2","document_id":"43240C1D","expansion_state":0,"options":{"engine":"r","label":"unnamed-chunk-39"},"row":20,"row_count":1,"visible":true},{"chunk_id":"coyicmfl6pmj2","chunk_label":"unnamed-chunk-7","document_id":"43240C1D","expansion_state":0,"options":{"engine":"r","label":"unnamed-chunk-24"},"row":67,"row_count":1,"visible":true},{"chunk_id":"curs3b6defwxk","chunk_label":"unnamed-chunk-8","document_id":"43240C1D","expansion_state":0,"options":{"engine":"r","label":"unnamed-chunk-25"},"row":97,"row_count":1,"visible":true},{"chunk_id":"c1qgfyebkdnmc","chunk_label":"unnamed-chunk-9","document_id":"43240C1D","expansion_state":0,"options":{"engine":"r","label":"unnamed-chunk-26"},"row":109,"row_count":1,"visible":true},{"chunk_id":"c56ed2ihpf21w","chunk_label":"unnamed-chunk-10","document_id":"43240C1D","expansion_state":0,"options":{"engine":"r","label":"unnamed-chunk-27"},"row":118,"row_count":1,"visible":true},{"chunk_id":"caenv0htqjply","chunk_label":"unnamed-chunk-11","document_id":"43240C1D","expansion_state":0,"options":{"engine":"r","label":"unnamed-chunk-28"},"row":124,"row_count":1,"visible":true},{"chunk_id":"c3vu1ywiilqmn","chunk_label":"unnamed-chunk-12","document_id":"43240C1D","expansion_state":0,"options":{"engine":"r","label":"unnamed-chunk-29"},"row":128,"row_count":1,"visible":true},{"chunk_id":"cd30bdlqqvd5g","chunk_label":"unnamed-chunk-13","document_id":"43240C1D","expansion_state":0,"options":{"engine":"r","label":"unnamed-chunk-22"},"row":134,"row_count":1,"visible":true},{"chunk_id":"c3mjmrqxmwopl","chunk_label":"unnamed-chunk-14","document_id":"43240C1D","expansion_state":0,"options":{"engine":"r","label":"unnamed-chunk-30"},"row":140,"row_count":1,"visible":true},{"chunk_id":"cgla64ycetbc8","chunk_label":"unnamed-chunk-15","document_id":"43240C1D","expansion_state":0,"options":{"engine":"r","label":"unnamed-chunk-16"},"row":147,"row_count":1,"visible":true},{"chunk_id":"cbkywzulrlraf","chunk_label":"unnamed-chunk-16","document_id":"43240C1D","expansion_state":0,"options":{"engine":"r","label":"unnamed-chunk-1"},"row":155,"row_count":1,"visible":true},{"chunk_id":"cvusb1hzr5uca","chunk_label":"unnamed-chunk-18","document_id":"43240C1D","expansion_state":0,"options":{"engine":"r","label":"unnamed-chunk-2"},"row":164,"row_count":1,"visible":true}],"doc_write_time":1515862158}